accuralai_google/__init__.py
accuralai_google/backend.py
accuralai_google-0.2.1.dist-info/METADATA
accuralai_google-0.2.1.dist-info/WHEEL
accuralai_google-0.2.1.dist-info/entry_points.txt
accuralai_google-0.2.1.dist-info/licenses/LICENSE
accuralai_google-0.2.1.dist-info/RECORD
