Metadata-Version: 2.4
Name: accuralai-google
Version: 0.2.1
Summary: Google GenAI backend adapter for the AccuralAI orchestration pipeline.
Project-URL: homepage, https://accural-ai.web.app/
Project-URL: repository, https://github.com/AccuralAI/accuralai-google
Project-URL: documentation, https://accuralai.readthedocs.io/en/latest/packages/accuralai-google/index.html
Author: AccuralAI Maintainers
License: Apache-2.0
License-File: LICENSE
Requires-Python: >=3.10
Requires-Dist: accuralai-core
Requires-Dist: google-genai>=0.3.0
Requires-Dist: pydantic>=2.5
Provides-Extra: dev
Requires-Dist: pytest; extra == 'dev'
Requires-Dist: pytest-anyio; extra == 'dev'
Requires-Dist: pytest-mock; extra == 'dev'
